{
    "id": "George-Winston-Piano-Sheet-Collection-ebook",
    "metadata": {
        "created_at": 1728831214000,
        "updated_at": 1728831214000,
        "published_at": null,
        "unpublished_at": null,
        "reviewed_at": null,
        "released_at": null,
        "expiration_date": null
    },
    "media": {
        "images": [
            {
                "url": "https://m.media-amazon.com/images/I/51jX35kR+ZL._SY445_SX342_.jpg",
                "alt_text": "George Winston - Piano Sheet Music Collection"
            }
        ],
        "videos": []
    },
    "listing": {
        "sku": "aFFwvdXMgRRy3JUrM2Zpk",
        "seo": {
            "meta_title": "George Winston - Piano Sheet Music Collection",
            "meta_description": "",
            "meta_keywords": "",
            "canonical_url": ""
        },
        "title": "George Winston - Piano Sheet Music Collection",
        "description": {
            "short": "",
            "long": ""
        },
        "categories": {},
        "tags": [],
        "status": {
            "availability": "",
            "lifecycle": "",
            "featured": false,
            "on_sale": false
        }
    },
    "details": {
        "brand": "",
        "model": "",
        "condition": "",
        "clearance": false,
        "legal": {
            "warranty_info": "",
            "return_policy": ""
        },
        "attributes": []
    },
    "variants": [],
    "reviews": {
        "total_count": 0,
        "average_rating": 0.0,
        "star_distribution": {
            "five": 0,
            "four": 0,
            "three": 0,
            "two": 0,
            "one": 0
        }
    }
}